MANIFEST.in
setup.py
docs/HISTORY.txt
src/dolmen/__init__.py
src/dolmen.blob.egg-info/PKG-INFO
src/dolmen.blob.egg-info/SOURCES.txt
src/dolmen.blob.egg-info/dependency_links.txt
src/dolmen.blob.egg-info/namespace_packages.txt
src/dolmen.blob.egg-info/not-zip-safe
src/dolmen.blob.egg-info/requires.txt
src/dolmen.blob.egg-info/top_level.txt
src/dolmen/blob/README.txt
src/dolmen/blob/__init__.py
src/dolmen/blob/access.py
src/dolmen/blob/configure.zcml
src/dolmen/blob/copy.py
src/dolmen/blob/file.py
src/dolmen/blob/ftesting.zcml
src/dolmen/blob/interfaces.py
src/dolmen/blob/property.py
src/dolmen/blob/storage.py
src/dolmen/blob/tests.py